django_viddler-1.3.6.dist-info/DESCRIPTION.rst
django_viddler-1.3.6.dist-info/METADATA
django_viddler-1.3.6.dist-info/RECORD
django_viddler-1.3.6.dist-info/WHEEL
django_viddler-1.3.6.dist-info/metadata.json
django_viddler-1.3.6.dist-info/pbr.json
django_viddler-1.3.6.dist-info/top_level.txt
viddler/__init__.py
viddler/admin.py
viddler/external_img.py
viddler/forms.py
viddler/models.py
viddler/settings.py
viddler/tasks.py
viddler/tests.py
viddler/urls.py
viddler/views.py
viddler/management/__init__.py
viddler/management/commands/__init__.py
viddler/management/commands/sync_viddler.py
viddler/migrations/0001_initial.py
viddler/migrations/__init__.py
viddler/static/viddler/placeholder.txt
viddler/templates/.DS_Store
viddler/templates/admin/.DS_Store
viddler/templates/admin/viddler/.DS_Store
viddler/templates/admin/viddler/viddlervideo/add_form.html
viddler/templates/admin/viddler/viddlervideo/change_form.html
viddler/templates/admin/viddler/viddlervideo/fieldset.html
